{
  "products": [
    {
      "id": 251,
      "title": "Van Cleef & Arpels Vintage Alhambra Necklace",
      "subtitle": "Vintage Alhambra",
      "brand": "van-cleef-arpels",
      "brandDisplay": "Van Cleef & Arpels",
      "size": "standard",
      "sizeDisplay": "42cm chain",
      "price": "high",
      "color": "gold",
      "colorDisplay": "Gold",
      "material": "18K Gold Plated",
      "featured": true,
      "rating": 5,
      "reviews": 15,
      "status": "available",
      "images": {
        "main": "https://via.placeholder.com/400x400/FFD700/FFFFFF?text=VCA+Necklace",
        "gallery": [
          "https://via.placeholder.com/400x400/FFD700/FFFFFF?text=VCA+Necklace",
          "https://via.placeholder.com/400x400/FFD700/FFFFFF?text=VCA+Detail+1",
          "https://via.placeholder.com/400x400/FFD700/FFFFFF?text=VCA+Detail+2"
        ],
        "thumbnail": "https://via.placeholder.com/400x400/FFD700/FFFFFF?text=VCA+Necklace"
      },
      "features": [
        "18K gold plated",
        "Signature clover motif",
        "Handcrafted excellence",
        "Timeless elegance"
      ],
      "description": "Exquisite Van Cleef & Arpels Vintage Alhambra necklace featuring the iconic four-leaf clover motif.",
      "specifications": {
        "Chain Length": "42cm",
        "Material": "18K Gold Plated",
        "Motif Size": "15mm"
      },
      "tags": [
        "Premium",
        "Luxury",
        "Jewelry",
        "Necklace"
      ],
      "category": "jewelry"
    },
    {
      "id": 252,
      "title": "Chanel Camellia Earrings",
      "subtitle": "Camellia Collection",
      "brand": "chanel",
      "brandDisplay": "Chanel Jewelry",
      "size": "standard",
      "sizeDisplay": "2cm diameter",
      "price": "high",
      "color": "white",
      "colorDisplay": "White Pearl",
      "material": "Pearl & Gold",
      "featured": false,
      "rating": 5,
      "reviews": 12,
      "status": "available",
      "images": {
        "main": "https://via.placeholder.com/400x400/F8F8FF/000000?text=Chanel+Earrings",
        "gallery": [
          "https://via.placeholder.com/400x400/F8F8FF/000000?text=Chanel+Earrings",
          "https://via.placeholder.com/400x400/F8F8FF/000000?text=Chanel+Detail+1",
          "https://via.placeholder.com/400x400/F8F8FF/000000?text=Chanel+Detail+2"
        ],
        "thumbnail": "https://via.placeholder.com/400x400/F8F8FF/000000?text=Chanel+Earrings"
      },
      "features": [
        "Signature camellia design",
        "Premium pearl finish",
        "Gold-tone hardware",
        "Comfortable wear"
      ],
      "description": "Elegant Chanel camellia earrings featuring the iconic flower motif with lustrous pearl finish.",
      "specifications": {
        "Diameter": "2cm",
        "Material": "Pearl & Gold-tone metal",
        "Closure": "Post back"
      },
      "tags": [
        "Premium",
        "Luxury",
        "Jewelry",
        "Earrings"
      ],
      "category": "jewelry"
    },
    {
      "id": 253,
      "title": "Dior Tribales Earrings",
      "subtitle": "Tribales Collection",
      "brand": "dior",
      "brandDisplay": "Dior Jewelry",
      "size": "standard",
      "sizeDisplay": "3cm drop",
      "price": "high",
      "color": "gold",
      "colorDisplay": "Gold",
      "material": "Gold Plated",
      "featured": false,
      "rating": 5,
      "reviews": 8,
      "status": "available",
      "images": {
        "main": "https://via.placeholder.com/400x400/FFD700/FFFFFF?text=Dior+Earrings",
        "gallery": [
          "https://via.placeholder.com/400x400/FFD700/FFFFFF?text=Dior+Earrings",
          "https://via.placeholder.com/400x400/FFD700/FFFFFF?text=Dior+Detail+1",
          "https://via.placeholder.com/400x400/FFD700/FFFFFF?text=Dior+Detail+2"
        ],
        "thumbnail": "https://via.placeholder.com/400x400/FFD700/FFFFFF?text=Dior+Earrings"
      },
      "features": [
        "Signature Dior design",
        "Gold-plated finish",
        "Comfortable fit",
        "Elegant drop style"
      ],
      "description": "Sophisticated Dior Tribales earrings showcasing the brand's signature elegance and craftsmanship.",
      "specifications": {
        "Drop Length": "3cm",
        "Material": "Gold Plated Metal",
        "Closure": "Post back"
      },
      "tags": [
        "Premium",
        "Luxury",
        "Jewelry",
        "Earrings"
      ],
      "category": "jewelry"
    },
    {
      "id": 254,
      "title": "Louis Vuitton Monogram Bracelet",
      "subtitle": "Monogram Collection",
      "brand": "louis-vuitton",
      "brandDisplay": "LV Jewelry",
      "size": "adjustable",
      "sizeDisplay": "16-18cm",
      "price": "high",
      "color": "gold",
      "colorDisplay": "Gold",
      "material": "Gold Plated",
      "featured": false,
      "rating": 5,
      "reviews": 10,
      "status": "available",
      "images": {
        "main": "https://via.placeholder.com/400x400/FFD700/FFFFFF?text=LV+Bracelet",
        "gallery": [
          "https://via.placeholder.com/400x400/FFD700/FFFFFF?text=LV+Bracelet",
          "https://via.placeholder.com/400x400/FFD700/FFFFFF?text=LV+Detail+1",
          "https://via.placeholder.com/400x400/FFD700/FFFFFF?text=LV+Detail+2"
        ],
        "thumbnail": "https://via.placeholder.com/400x400/FFD700/FFFFFF?text=LV+Bracelet"
      },
      "features": [
        "Iconic monogram pattern",
        "Adjustable size",
        "Premium gold plating",
        "Signature LV charm"
      ],
      "description": "Luxurious Louis Vuitton monogram bracelet featuring the iconic LV pattern and signature charm.",
      "specifications": {
        "Size": "16-18cm adjustable",
        "Material": "Gold Plated Metal",
        "Closure": "Adjustable chain"
      },
      "tags": [
        "Premium",
        "Luxury",
        "Jewelry",
        "Bracelet"
      ],
      "category": "jewelry"
    },
    {
      "id": 255,
      "title": "Tiffany & Co. Return to Tiffany Ring",
      "subtitle": "Return to Tiffany",
      "brand": "tiffany",
      "brandDisplay": "Tiffany",
      "size": "adjustable",
      "sizeDisplay": "Size 6-8",
      "price": "high",
      "color": "silver",
      "colorDisplay": "Silver",
      "material": "Sterling Silver",
      "featured": true,
      "rating": 5,
      "reviews": 20,
      "status": "available",
      "images": {
        "main": "https://via.placeholder.com/400x400/C0C0C0/000000?text=Tiffany+Ring",
        "gallery": [
          "https://via.placeholder.com/400x400/C0C0C0/000000?text=Tiffany+Ring",
          "https://via.placeholder.com/400x400/C0C0C0/000000?text=Tiffany+Detail+1",
          "https://via.placeholder.com/400x400/C0C0C0/000000?text=Tiffany+Detail+2"
        ],
        "thumbnail": "https://via.placeholder.com/400x400/C0C0C0/000000?text=Tiffany+Ring"
      },
      "features": [
        "Iconic Tiffany design",
        "Sterling silver construction",
        "Adjustable sizing",
        "Signature blue box included"
      ],
      "description": "Classic Tiffany & Co. Return to Tiffany ring in sterling silver with signature heart charm.",
      "specifications": {
        "Size Range": "6-8 (adjustable)",
        "Material": "Sterling Silver",
        "Width": "3mm"
      },
      "tags": [
        "Premium",
        "Luxury",
        "Jewelry",
        "Ring"
      ],
      "category": "jewelry"
    },
    {
      "id": 256,
      "title": "Van Cleef & Arpels Frivole ring, single flower, small model",
      "subtitle": "Frivole ring, single flower, small model",
      "brand": "van-cleef-arpels",
      "brandDisplay": "Van Cleef & Arpels",
      "size": "medium",
      "sizeDisplay": "Standard Size",
      "price": "high",
      "color": "gold",
      "colorDisplay": "Gold",
      "material": "Premium Materials",
      "featured": false,
      "rating": 5,
      "reviews": 8,
      "status": "available",
      "images": {
        "main": "https://github.com/yusuf-server/picx-images-hosting/raw/master/jewelry/Van Cleef & Arpels_Frivole ring, single flower, small model/f6baa4b577a0.webp",
        "gallery": [
          "https://github.com/yusuf-server/picx-images-hosting/raw/master/jewelry/Van Cleef & Arpels_Frivole ring, single flower, small model/f6baa4b577a0.webp",
          "https://github.com/yusuf-server/picx-images-hosting/raw/master/jewelry/Van Cleef & Arpels_Frivole ring, single flower, small model/3c8b2576ace4.webp",
          "https://github.com/yusuf-server/picx-images-hosting/raw/master/jewelry/Van Cleef & Arpels_Frivole ring, single flower, small model/03784213e2b8.webp"
        ],
        "thumbnail": "https://github.com/yusuf-server/picx-images-hosting/raw/master/jewelry/Van Cleef & Arpels_Frivole ring, single flower, small model/f6baa4b577a0.webp"
      },
      "features": [
        "Premium craftsmanship",
        "Exquisite design",
        "High-quality materials",
        "Timeless elegance"
      ],
      "description": "Exquisite Van Cleef & Arpels jewelry piece featuring exceptional craftsmanship and timeless design.",
      "specifications": {
        "Size": "SIZE_49, SIZE_47, SIZE_46, SIZE_48, SIZE_52, SIZE_55, SIZE_54, SIZE_53, SIZE_44, SIZE_43, SIZE_42, SIZE_45, SIZE_51, SIZE_50"
      },
      "tags": [
        "Premium",
        "Luxury",
        "Jewelry",
        "Elegant"
      ],
      "category": "jewelry",
      "detailedDescription": "Frivole ring. solitaire. petite model. 18K yellow gold. round diamonds; diamond quality DEF. IF to VVS.\nMODEL\nVCARP2V000\nGEM\ngemDiamonds: 43 gems. 0.81 carats"
    }
  ],
  "filters": {
    "brands": [
      {
        "value": "all",
        "label": "All Jewelry Brands"
      },
      {
        "value": "van-cleef-arpels",
        "label": "Van Cleef & Arpels"
      },
      {
        "value": "chanel",
        "label": "Chanel Jewelry"
      },
      {
        "value": "dior",
        "label": "Dior Jewelry"
      },
      {
        "value": "louis-vuitton",
        "label": "LV Jewelry"
      },
      {
        "value": "tiffany",
        "label": "Tiffany"
      },
      {
        "value": "cartier",
        "label": "Cartier"
      },
      {
        "value": "bulgari",
        "label": "Bulgari"
      }
    ]
  },
  "lastUpdated": "2025-07-09T00:07:01.617567"
}